ichello-0.0.5.dist-info/RECORD
ichello-0.0.5.dist-info/WHEEL
ichello-0.0.5.dist-info/METADATA
ichello-0.0.5.dist-info/licenses/LICENSE
ichello/hello.py
ichello/ichello_ext.abi3.so
ichello/__init__.py
