Metadata-Version: 2.1
Name: ichello
Version: 0.0.5
Summary: A sample Python app
Keywords: Sample App
Author-Email: "James Grogan, Irish Centre for High End Computing" <james.grogan@ichec.ie>
Classifier: Development Status :: 3 - Alpha
Classifier: Programming Language :: Python :: 3
Classifier: Operating System :: OS Independent
Project-URL: Repository, https://github.com/jmsgrogan/sample-python-deploy
Project-URL: Homepage, https://github.com/jmsgrogan/sample-python-deploy
Requires-Python: >=3.9
